defuse/__init__.py
defuse/cli.py
defuse/src/__init__.py
defuse/src/module_file.py
defuse-0.2.0.dist-info/licenses/LICENSE
defuse-0.2.0.dist-info/METADATA
defuse-0.2.0.dist-info/WHEEL
defuse-0.2.0.dist-info/entry_points.txt
defuse-0.2.0.dist-info/top_level.txt
defuse-0.2.0.dist-info/RECORD
